{"Level":5,"width":8,"height":8,"gameTime":120,"itemData":[{"itemType":0,"index":2},{"itemType":0,"index":2},{"itemType":0,"index":0},{"itemType":0,"index":1},{"itemType":0,"index":1},{"itemType":0,"index":0},{"itemType":0,"index":2},{"itemType":0,"index":2},{"itemType":0,"index":2},{"itemType":0,"index":0},{"itemType":0,"index":1},{"itemType":0,"index":3},{"itemType":0,"index":3},{"itemType":0,"index":1},{"itemType":0,"index":0},{"itemType":0,"index":2},{"itemType":0,"index":0},{"itemType":0,"index":1},{"itemType":0,"index":3},{"itemType":2,"index":0},{"itemType":2,"index":0},{"itemType":0,"index":3},{"itemType":0,"index":1},{"itemType":0,"index":0},{"itemType":0,"index":1},{"itemType":0,"index":3},{"itemType":2,"index":0},{"itemType":2,"index":0},{"itemType":2,"index":0},{"itemType":2,"index":0},{"itemType":0,"index":3},{"itemType":0,"index":1},{"itemType":0,"index":1},{"itemType":0,"index":3},{"itemType":2,"index":0},{"itemType":2,"index":0},{"itemType":2,"index":0},{"itemType":2,"index":0},{"itemType":0,"index":3},{"itemType":0,"index":1},{"itemType":0,"index":0},{"itemType":0,"index":1},{"itemType":0,"index":3},{"itemType":2,"index":0},{"itemType":2,"index":0},{"itemType":0,"index":3},{"itemType":0,"index":1},{"itemType":0,"index":0},{"itemType":0,"index":2},{"itemType":0,"index":0},{"itemType":0,"index":1},{"itemType":0,"index":3},{"itemType":0,"index":3},{"itemType":0,"index":1},{"itemType":0,"index":0},{"itemType":0,"index":2},{"itemType":0,"index":2},{"itemType":0,"index":2},{"itemType":0,"index":0},{"itemType":0,"index":1},{"itemType":0,"index":1},{"itemType":0,"index":0},{"itemType":0,"index":2},{"itemType":0,"index":2}]}